decomp_settings-0.0.9.dist-info/METADATA
decomp_settings-0.0.9.dist-info/WHEEL
decomp_settings-0.0.9.dist-info/licenses/LICENSE-APACHE
decomp_settings-0.0.9.dist-info/licenses/LICENSE-MIT
decomp_settings/__init__.py
decomp_settings/__init__.pyi
decomp_settings/decomp_settings.pypy310-pp73-s390x-linux-gnu.so
decomp_settings/py.typed
decomp_settings-0.0.9.dist-info/RECORD
