Metadata-Version: 2.4
Name: decomp_settings
Version: 0.0.9
Classifier: Programming Language :: Rust
Classifier: Programming Language :: Python :: Implementation :: CPython
Classifier: Programming Language :: Python :: Implementation :: PyPy
Requires-Dist: pytest ; extra == 'test'
Requires-Dist: pytest-cov ; extra == 'test'
Provides-Extra: test
License-File: LICENSE-APACHE
License-File: LICENSE-MIT
Summary: A library for reading the decomp.yaml settings file
Author: Ethan Roseman <ethteck@gmail.com>
Author-email: Ethan Roseman <ethteck@gmail.com>
License: MIT OR Apache-2.0
Requires-Python: >=3.9
Project-URL: Homepage, https://github.com/ethteck/decomp_settings
Project-URL: Bug Tracker, https://github.com/ethteck/decomp_settings/issues
